{
  "project_info": {
    "project_number": "860295591595",
    "firebase_url": "https://nt-bargain-hunter-b69bf.firebaseio.com",
    "project_id": "nt-bargain-hunter-b69bf",
    "storage_bucket": "nt-bargain-hunter-b69bf.appspot.com"
  },
  "client": [
    {
      "client_info": {
        "mobilesdk_app_id": "1:860295591595:android:0b5911de84fe79f00ee9ee",
        "android_client_info": {
          "package_name": "com.example.ntbargainhunter"
        }
      },
      "oauth_client": [
        {
          "client_id": "860295591595-bcbi4csf2k4hfiogrdulphn05ro4fluj.apps.googleusercontent.com",
          "client_type": 1,
          "android_info": {
            "package_name": "com.example.ntbargainhunter",
            "certificate_hash": "20ebb97ce3b8ab625b12fe27c8624e2cdcad0024"
          }
        },
        {
          "client_id": "860295591595-9memopdo2068ovj15plau8gsikg2l408.apps.googleusercontent.com",
          "client_type": 1,
          "android_info": {
            "package_name": "com.example.ntbargainhunter",
            "certificate_hash": "6e698ed2ab7c6bfec1766f43512fd3767924be16"
          }
        },
        {
          "client_id": "860295591595-unihhu9i4dabh4m249bkie7du2bhu10o.apps.googleusercontent.com",
          "client_type": 3
        }
      ],
      "api_key": [
        {
          "current_key": "AIzaSyACaATSZhxRWUbIhfaMqSLf4AsoZfOUQPo"
        }
      ],
      "services": {
        "appinvite_service": {
          "other_platform_oauth_client": [
            {
              "client_id": "860295591595-unihhu9i4dabh4m249bkie7du2bhu10o.apps.googleusercontent.com",
              "client_type": 3
            }
          ]
        }
      }
    }
  ],
  "configuration_version": "1"
}